babylab/__init__.py
babylab/api.py
babylab/globals.py
babylab/utils.py
babylab-0.8.0.dist-info/METADATA
babylab-0.8.0.dist-info/WHEEL
babylab-0.8.0.dist-info/licenses/LICENSE
babylab-0.8.0.dist-info/RECORD
