Metadata-Version: 2.4
Name: babylab
Version: 0.8.0
Summary: A GUI for the SJD Babylab REDCap database
Project-URL: Documentation, https://github.com/NeuroDevComp/babylab-redcap#readme
Project-URL: Issues, https://github.com/NeuroDevComp/babylab-redcap/issues
Project-URL: Source, https://github.com/NeuroDevComp/babylab-redcap
Author-email: gongcastro <gongarciacastro@gmail.com>
License-Expression: MIT
License-File: LICENSE
Requires-Python: >=3.10
Requires-Dist: dateutils>=0.6.12
Requires-Dist: dotenv>=0.9.9
Requires-Dist: polars>=1.33.1
Requires-Dist: pyarrow>=22.0.0
Requires-Dist: requests>=2.32.5
